LICENSE
MANIFEST.in
README
README.rst
nosetimelimit.py
setup.py
nose_timelimit.egg-info/PKG-INFO
nose_timelimit.egg-info/SOURCES.txt
nose_timelimit.egg-info/dependency_links.txt
nose_timelimit.egg-info/entry_points.txt
nose_timelimit.egg-info/not-zip-safe
nose_timelimit.egg-info/requires.txt
nose_timelimit.egg-info/top_level.txt